README
setup.py
pyfspot/__init__.py
pyfspot/controller.py
pyfspot/main.py
pyfspot/models.py
pyfspot/tests.py
pyfspot/utils.py
pyfspot.egg-info/PKG-INFO
pyfspot.egg-info/SOURCES.txt
pyfspot.egg-info/dependency_links.txt
pyfspot.egg-info/entry_points.txt
pyfspot.egg-info/requires.txt
pyfspot.egg-info/top_level.txt