Metadata-Version: 1.1
Name: pyfspot
Version: 0.2
Summary: Perform operations on your F-Spot database.
Home-page: https://github.com/leplatrem/pyfspot/
Author: Mathieu Leplatre
Author-email: contact@mathieu-leplatre.info
License: LGPL
Download-URL: http://pypi.python.org/pypi/pyfspot/
Keywords: f-spot
Platform: any
Classifier: Programming Language :: Python :: 2.5
Classifier: Operating System :: OS Independent
Classifier: Intended Audience :: End Users/Desktop
Classifier: Natural Language :: English
Classifier: Topic :: Utilities
Classifier: Development Status :: 3 - Alpha
Provides: pyfspot
